hardware/ip/voltage_display_ip/rtl/voltage_display_scan.v
`timescale 1ns / 1ps

module voltage_display_scan #(
    parameter integer SCAN_TICK_CYCLES = 100_000
)(
    input  wire       clk,
    input  wire       reset_p,
    input  wire       display_valid,
    input  wire [3:0] digit3,
    input  wire [3:0] digit2,
    input  wire [3:0] digit1,
    input  wire [3:0] digit0,
    output reg  [3:0] an,
    output reg  [6:0] seg,
    output reg        dp,
    output wire       frame_boundary
);

    reg [31:0] scan_counter;
    reg [1:0]  scan_index;
    reg [3:0]  active_digit;

    assign frame_boundary =
        (scan_index == 2'd3) &&
        ((SCAN_TICK_CYCLES <= 1) ||
         (scan_counter >= (SCAN_TICK_CYCLES - 1)));

    always @(posedge clk or posedge reset_p) begin
        if (reset_p) begin
            scan_counter <= 32'd0;
            scan_index   <= 2'd0;
        end
        else if (SCAN_TICK_CYCLES <= 1) begin
            scan_counter <= 32'd0;
            scan_index   <= scan_index + 1'b1;
        end
        else if (scan_counter >= (SCAN_TICK_CYCLES - 1)) begin
            scan_counter <= 32'd0;
            scan_index   <= scan_index + 1'b1;
        end
        else begin
            scan_counter <= scan_counter + 1'b1;
        end
    end

    always @(*) begin
        an           = 4'b1111;
        seg          = 7'b1111111;
        dp           = 1'b1;
        active_digit = 4'd0;

        if (!reset_p) begin
            case (scan_index)
                2'd0: begin
                    an           = 4'b1110;
                    active_digit = digit0;
                end
                2'd1: begin
                    an           = 4'b1101;
                    active_digit = digit1;
                end
                2'd2: begin
                    an           = 4'b1011;
                    active_digit = digit2;
                end
                2'd3: begin
                    an           = 4'b0111;
                    active_digit = digit3;
                end
                default: begin
                    an           = 4'b1111;
                    active_digit = 4'd0;
                end
            endcase

            if (display_valid) begin
                seg = digit_to_segments(active_digit);
                if (scan_index == 2'd3)
                    dp = 1'b0;
            end
            else begin
                seg = 7'b0111111;
                dp  = 1'b1;
            end
        end
    end

    function [6:0] digit_to_segments;
        input [3:0] digit;
        begin
            case (digit)
                4'd0: digit_to_segments = 7'b1000000;
                4'd1: digit_to_segments = 7'b1111001;
                4'd2: digit_to_segments = 7'b0100100;
                4'd3: digit_to_segments = 7'b0110000;
                4'd4: digit_to_segments = 7'b0011001;
                4'd5: digit_to_segments = 7'b0010010;
                4'd6: digit_to_segments = 7'b0000010;
                4'd7: digit_to_segments = 7'b1111000;
                4'd8: digit_to_segments = 7'b0000000;
                4'd9: digit_to_segments = 7'b0010000;
                default: digit_to_segments = 7'b1111111;
            endcase
        end
    endfunction

endmodule

hardware/custom_ip/voltage_display_ip_1_0/packaged_ip/voltage_display_ip_1.0/src/voltage_display_bcd.v
`timescale 1ns / 1ps

module voltage_display_bcd (
    input  wire [11:0] millivolt,
    output reg  [3:0]  digit3,
    output reg  [3:0]  digit2,
    output reg  [3:0]  digit1,
    output reg  [3:0]  digit0
);

    reg [27:0] shift_register;
    integer index;

    always @(*) begin
        shift_register       = 28'd0;
        shift_register[11:0] = millivolt;

        // Twelve-bit combinational Double-Dabble conversion.
        for (index = 0; index < 12; index = index + 1) begin
            if (shift_register[15:12] >= 4'd5)
                shift_register[15:12] =
                    shift_register[15:12] + 2'd3;
            if (shift_register[19:16] >= 4'd5)
                shift_register[19:16] =
                    shift_register[19:16] + 2'd3;
            if (shift_register[23:20] >= 4'd5)
                shift_register[23:20] =
                    shift_register[23:20] + 2'd3;
            if (shift_register[27:24] >= 4'd5)
                shift_register[27:24] =
                    shift_register[27:24] + 2'd3;
            shift_register = shift_register << 1;
        end

        digit3 = shift_register[27:24];
        digit2 = shift_register[23:20];
        digit1 = shift_register[19:16];
        digit0 = shift_register[15:12];
    end

endmodule

hardware/custom_ip/voltage_display_ip_1_0/rtl/voltage_display_convert.v
`timescale 1ns / 1ps

module voltage_display_convert (
    input  wire [11:0] adc_raw,
    output reg  [11:0] millivolt
);

    reg [23:0] scaled_value;
    reg [12:0] quotient_base;
    reg [12:0] quotient_correction_sum;
    reg [12:0] converted_value;

    always @(*) begin
        scaled_value = ({12'd0, adc_raw} * 24'd3300) + 24'd2047;

        // Exact constant division by 4095 without a divider.
        // Let N = H*4096 + L. Then:
        //   floor(N/4095) = H + floor((H+L)/4095).
        // In this design H+L is below 8190, so the correction is 0 or 1.
        quotient_base = {1'b0, scaled_value[23:12]};
        quotient_correction_sum =
            {1'b0, scaled_value[11:0]} + quotient_base;
        if (quotient_correction_sum >= 13'd4095)
            converted_value = quotient_base + 1'b1;
        else
            converted_value = quotient_base;

        if (converted_value > 13'd3300)
            millivolt = 12'd3300;
        else
            millivolt = converted_value[11:0];
    end

endmodule

voltage_display_ip_final_delivery/voltage_display_ip/packaged_ip/voltage_display_ip_1.0/src/voltage_display_ip.v
`timescale 1ns / 1ps

module voltage_display_ip #(
    parameter integer SCAN_TICK_CYCLES = 100_000
)(
    input  wire        clk,
    input  wire        reset_p,
    input  wire [11:0] current_adc,
    input  wire        display_valid,
    output wire [3:0]  an,
    output wire [6:0]  seg,
    output wire        dp
);

    reg  [11:0] frame_adc;
    reg         frame_valid;
    wire [11:0] frame_millivolt;
    wire [3:0]  digit3;
    wire [3:0]  digit2;
    wire [3:0]  digit1;
    wire [3:0]  digit0;
    wire        frame_boundary;

    always @(posedge clk or posedge reset_p) begin
        if (reset_p) begin
            frame_adc   <= 12'd0;
            frame_valid <= 1'b0;
        end
        else if (frame_boundary) begin
            frame_adc   <= current_adc;
            frame_valid <= display_valid;
        end
    end

    voltage_display_convert u_voltage_display_convert (
        .adc_raw    (frame_adc),
        .millivolt  (frame_millivolt)
    );

    voltage_display_bcd u_voltage_display_bcd (
        .millivolt (frame_millivolt),
        .digit3    (digit3),
        .digit2    (digit2),
        .digit1    (digit1),
        .digit0    (digit0)
    );

    voltage_display_scan #(
        .SCAN_TICK_CYCLES (SCAN_TICK_CYCLES)
    ) u_voltage_display_scan (
        .clk            (clk),
        .reset_p        (reset_p),
        .display_valid  (frame_valid),
        .digit3         (digit3),
        .digit2         (digit2),
        .digit1         (digit1),
        .digit0         (digit0),
        .an             (an),
        .seg            (seg),
        .dp             (dp),
        .frame_boundary (frame_boundary)
    );

endmodule

voltage_display_ip_final_delivery/voltage_display_ip/packaged_ip/voltage_display_ip_1.0/sim/tb_voltage_display_ip.v
`timescale 1ns / 1ps

module tb_voltage_display_ip;

    localparam integer SCAN_TICK_CYCLES = 2;

    reg         clk;
    reg         reset_p;
    reg  [11:0] current_adc;
    reg         display_valid;
    wire [3:0]  an;
    wire [6:0]  seg;
    wire        dp;

    reg  [11:0] conversion_adc;
    wire [11:0] conversion_mv;
    wire [3:0]  conversion_digit3;
    wire [3:0]  conversion_digit2;
    wire [3:0]  conversion_digit1;
    wire [3:0]  conversion_digit0;

    reg         decoder_valid;
    reg  [3:0]  decoder_digit;
    wire [3:0]  decoder_an;
    wire [6:0]  decoder_seg;
    wire        decoder_dp;
    wire        decoder_boundary;

    integer errors;
    integer index;
    integer expected_mv;
    reg [3:0] expected_digit3;
    reg [3:0] expected_digit2;
    reg [3:0] expected_digit1;
    reg [3:0] expected_digit0;

    voltage_display_ip #(
        .SCAN_TICK_CYCLES (SCAN_TICK_CYCLES)
    ) dut (
        .clk           (clk),
        .reset_p       (reset_p),
        .current_adc   (current_adc),
        .display_valid (display_valid),
        .an            (an),
        .seg           (seg),
        .dp            (dp)
    );

    voltage_display_convert u_conversion_check (
        .adc_raw   (conversion_adc),
        .millivolt (conversion_mv)
    );

    voltage_display_bcd u_bcd_check (
        .millivolt (conversion_mv),
        .digit3    (conversion_digit3),
        .digit2    (conversion_digit2),
        .digit1    (conversion_digit1),
        .digit0    (conversion_digit0)
    );

    voltage_display_scan #(
        .SCAN_TICK_CYCLES (SCAN_TICK_CYCLES)
    ) u_decoder_check (
        .clk            (clk),
        .reset_p        (reset_p),
        .display_valid  (decoder_valid),
        .digit3         (decoder_digit),
        .digit2         (decoder_digit),
        .digit1         (decoder_digit),
        .digit0         (decoder_digit),
        .an             (decoder_an),
        .seg            (decoder_seg),
        .dp             (decoder_dp),
        .frame_boundary (decoder_boundary)
    );

    always #5 clk = ~clk;

    function [6:0] expected_segment;
        input [3:0] digit;
        begin
            case (digit)
                4'd0: expected_segment = 7'b1000000;
                4'd1: expected_segment = 7'b1111001;
                4'd2: expected_segment = 7'b0100100;
                4'd3: expected_segment = 7'b0110000;
                4'd4: expected_segment = 7'b0011001;
                4'd5: expected_segment = 7'b0010010;
                4'd6: expected_segment = 7'b0000010;
                4'd7: expected_segment = 7'b1111000;
                4'd8: expected_segment = 7'b0000000;
                4'd9: expected_segment = 7'b0010000;
                default: expected_segment = 7'b1111111;
            endcase
        end
    endfunction

    task record_error;
        input [8*120-1:0] message;
        begin
            errors = errors + 1;
            $display("ERROR: %0s at %0t", message, $time);
        end
    endtask

    task wait_main_an;
        input [3:0] expected_an;
        integer guard;
        begin
            guard = 0;
            while ((an !== expected_an) && (guard < 40)) begin
                @(negedge clk);
                guard = guard + 1;
            end
            if (an !== expected_an)
                record_error("timeout waiting for main anode");
        end
    endtask

    task wait_decoder_an;
        input [3:0] expected_an;
        integer guard;
        begin
            guard = 0;
            while ((decoder_an !== expected_an) && (guard < 40)) begin
                @(negedge clk);
                guard = guard + 1;
            end
            if (decoder_an !== expected_an)
                record_error("timeout waiting for decoder anode");
        end
    endtask

    task check_main_digit;
        input [3:0] expected_an;
        input [6:0] expected_seg;
        input       expected_dp;
        begin
            wait_main_an(expected_an);
            if (seg !== expected_seg)
                record_error("main segment pattern mismatch");
            if (dp !== expected_dp)
                record_error("main decimal point mismatch");
            if (!((an == 4'b1110) || (an == 4'b1101) ||
                  (an == 4'b1011) || (an == 4'b0111)))
                record_error("more or fewer than one anode active");
        end
    endtask

    task check_frame;
        input [3:0] e3;
        input [3:0] e2;
        input [3:0] e1;
        input [3:0] e0;
        input       valid_value;
        begin
            wait_main_an(4'b0111);
            wait_main_an(4'b1110);
            if (valid_value)
                check_main_digit(4'b1110, expected_segment(e0), 1'b1);
            else
                check_main_digit(4'b1110, 7'b0111111, 1'b1);
            if (valid_value)
                check_main_digit(4'b1101, expected_segment(e1), 1'b1);
            else
                check_main_digit(4'b1101, 7'b0111111, 1'b1);
            if (valid_value)
                check_main_digit(4'b1011, expected_segment(e2), 1'b1);
            else
                check_main_digit(4'b1011, 7'b0111111, 1'b1);
            if (valid_value)
                check_main_digit(4'b0111, expected_segment(e3), 1'b0);
            else
                check_main_digit(4'b0111, 7'b0111111, 1'b1);
        end
    endtask

    task apply_and_check;
        input [11:0] adc_value;
        input [3:0]  e3;
        input [3:0]  e2;
        input [3:0]  e1;
        input [3:0]  e0;
        begin
            current_adc   = adc_value;
            display_valid = 1'b1;
            check_frame(e3, e2, e1, e0, 1'b1);
        end
    endtask

    initial begin
`ifdef VOLTAGE_DISPLAY_STANDALONE_VCD
        $dumpfile("voltage_display_ip.vcd");
        $dumpvars(0, tb_voltage_display_ip);
`endif

        clk            = 1'b0;
        reset_p        = 1'b0;
        current_adc    = 12'd0;
        display_valid  = 1'b0;
        conversion_adc = 12'd0;
        decoder_valid  = 1'b1;
        decoder_digit  = 4'd0;
        errors         = 0;

        // Active-high asynchronous reset and reset output blanking.
        #3 reset_p = 1'b1;
        #1;
        if (an !== 4'b1111 || seg !== 7'b1111111 || dp !== 1'b1)
            record_error("FND outputs are not all off during reset");
        if (decoder_an !== 4'b1111 ||
            decoder_seg !== 7'b1111111 || decoder_dp !== 1'b1)
            record_error("decoder outputs are not all off during reset");

        #7 reset_p = 1'b0;

        // Invalid display, dash font and DP off.
        display_valid = 1'b0;
        check_frame(4'd0, 4'd0, 4'd0, 4'd0, 1'b0);

        // Conversion formula, saturation bound and BCD for all ADC codes.
        for (index = 0; index < 4096; index = index + 1) begin
            conversion_adc = index[11:0];
            #1;
            expected_mv = ((index * 3300) + 2047) / 4095;
            if (expected_mv > 3300)
                expected_mv = 3300;
            expected_digit3 = expected_mv / 1000;
            expected_digit2 = (expected_mv / 100) % 10;
            expected_digit1 = (expected_mv / 10) % 10;
            expected_digit0 = expected_mv % 10;
            if (conversion_mv !== expected_mv[11:0])
                record_error("ADC to millivolt conversion mismatch");
            if (conversion_mv > 12'd3300)
                record_error("millivolt saturation exceeded 3300");
            if ({conversion_digit3, conversion_digit2,
                 conversion_digit1, conversion_digit0} !==
                {expected_digit3, expected_digit2,
                 expected_digit1, expected_digit0})
                record_error("binary to BCD conversion mismatch");
        end

        conversion_adc = 12'd0;    #1;
        if ({conversion_digit3, conversion_digit2,
             conversion_digit1, conversion_digit0} !== 16'h0000)
            record_error("BCD mismatch for 0 mV");
        conversion_adc = 12'd409;  #1;
        if (conversion_mv !== 12'd330)
            record_error("ADC 409 did not convert to 330 mV");
        conversion_adc = 12'd2048; #1;
        if (conversion_mv !== 12'd1650)
            record_error("ADC 2048 did not convert to 1650 mV");
        conversion_adc = 12'd3102; #1;
        if (conversion_mv !== 12'd2500)
            record_error("ADC 3102 did not convert to 2500 mV");
        conversion_adc = 12'd4095; #1;
        if (conversion_mv !== 12'd3300)
            record_error("ADC 4095 did not convert to 3300 mV");

        // All decimal fonts, anode order, one-hot activation and DP position.
        for (index = 0; index < 10; index = index + 1) begin
            decoder_digit = index[3:0];
            decoder_valid = 1'b1;
            wait_decoder_an(4'b0111);
            wait_decoder_an(4'b1110);
            if (decoder_seg !== expected_segment(index[3:0]) ||
                decoder_dp !== 1'b1)
                record_error("digit0 font/anode/DP mismatch");
            wait_decoder_an(4'b1101);
            if (decoder_seg !== expected_segment(index[3:0]) ||
                decoder_dp !== 1'b1)
                record_error("digit1 font/anode/DP mismatch");
            wait_decoder_an(4'b1011);
            if (decoder_seg !== expected_segment(index[3:0]) ||
                decoder_dp !== 1'b1)
                record_error("digit2 font/anode/DP mismatch");
            wait_decoder_an(4'b0111);
            if (decoder_seg !== expected_segment(index[3:0]) ||
                decoder_dp !== 1'b0)
                record_error("digit3 font/anode/DP mismatch");
        end

        decoder_valid = 1'b0;
        wait_decoder_an(4'b1110);
        if (decoder_seg !== 7'b0111111 || decoder_dp !== 1'b1)
            record_error("dash pattern or invalid DP mismatch");

        // Required displayed voltages.
        apply_and_check(12'd0,    4'd0, 4'd0, 4'd0, 4'd0);
        apply_and_check(12'd409,  4'd0, 4'd3, 4'd3, 4'd0);
        apply_and_check(12'd2048, 4'd1, 4'd6, 4'd5, 4'd0);
        apply_and_check(12'd3102, 4'd2, 4'd5, 4'd0, 4'd0);
        apply_and_check(12'd4095, 4'd3, 4'd3, 4'd0, 4'd0);

        // Mid-frame ADC change: old frame must finish, next frame is all new.
        current_adc   = 12'd2048;
        display_valid = 1'b1;
        check_frame(4'd1, 4'd6, 4'd5, 4'd0, 1'b1);
        wait_main_an(4'b1110);
        check_main_digit(4'b1110, expected_segment(4'd0), 1'b1);
        wait_main_an(4'b1101);
        current_adc = 12'd4095;
        check_main_digit(4'b1101, expected_segment(4'd5), 1'b1);
        check_main_digit(4'b1011, expected_segment(4'd6), 1'b1);
        check_main_digit(4'b0111, expected_segment(4'd1), 1'b0);
        check_main_digit(4'b1110, expected_segment(4'd0), 1'b1);
        check_main_digit(4'b1101, expected_segment(4'd0), 1'b1);
        check_main_digit(4'b1011, expected_segment(4'd3), 1'b1);
        check_main_digit(4'b0111, expected_segment(4'd3), 1'b0);

        // Mid-frame valid change: no mixed frame, dashes within one frame.
        current_adc   = 12'd3102;
        display_valid = 1'b1;
        check_frame(4'd2, 4'd5, 4'd0, 4'd0, 1'b1);
        wait_main_an(4'b1110);
        check_main_digit(4'b1110, expected_segment(4'd0), 1'b1);
        wait_main_an(4'b1101);
        display_valid = 1'b0;
        check_main_digit(4'b1101, expected_segment(4'd0), 1'b1);
        check_main_digit(4'b1011, expected_segment(4'd5), 1'b1);
        check_main_digit(4'b0111, expected_segment(4'd2), 1'b0);
        check_main_digit(4'b1110, 7'b0111111, 1'b1);
        check_main_digit(4'b1101, 7'b0111111, 1'b1);
        check_main_digit(4'b1011, 7'b0111111, 1'b1);
        check_main_digit(4'b0111, 7'b0111111, 1'b1);

        // Invalid-to-valid recovery.
        current_adc   = 12'd409;
        display_valid = 1'b1;
        check_frame(4'd0, 4'd3, 4'd3, 4'd0, 1'b1);

        // Reset after operation and verify scan resumes.
        #2 reset_p = 1'b1;
        #1;
        if (an !== 4'b1111 || seg !== 7'b1111111 || dp !== 1'b1)
            record_error("asynchronous reset failed after operation");
        #4 reset_p = 1'b0;
        current_adc   = 12'd4095;
        display_valid = 1'b1;
        check_frame(4'd3, 4'd3, 4'd0, 4'd0, 1'b1);

        if (errors == 0)
            $display("VOLTAGE_DISPLAY_IP TEST PASS");
        else
            $display("VOLTAGE_DISPLAY_IP TEST FAIL: %0d error(s)", errors);

        $finish;
    end

endmodule

voltage_display_ip_final_delivery/voltage_display_ip/reports/voltage_display_ip.vcd
$date
   Tue Jul 28 06:49:29 2026
$end

$version
  2024.2.0
$end

$timescale
  1ps
$end

$scope module tb_voltage_display_ip $end
$var reg 1 y clk $end
$var reg 1 z reset_p $end
$var reg 12 { current_adc [11:0] $end
$var reg 1 | display_valid $end
$var wire 4 A an [3:0] $end
$var wire 7 B seg [6:0] $end
$var wire 1 C dp $end
$var reg 12 } conversion_adc [11:0] $end
$var wire 12 M conversion_mv [11:0] $end
$var wire 4 ~ conversion_digit3 [3:0] $end
$var wire 4 !! conversion_digit2 [3:0] $end
$var wire 4 "! conversion_digit1 [3:0] $end
$var wire 4 #! conversion_digit0 [3:0] $end
$var reg 1 $! decoder_valid $end
$var reg 4 %! decoder_digit [3:0] $end
$var wire 4 &! decoder_an [3:0] $end
$var wire 7 '! decoder_seg [6:0] $end
$var wire 1 (! decoder_dp $end
$var wire 1 ` decoder_boundary $end
$var integer 32 )! errors [31:0] $end
$var integer 32 *! index [31:0] $end
$var integer 32 +! expected_mv [31:0] $end
$var reg 4 ,! expected_digit3 [3:0] $end
$var reg 4 -! expected_digit2 [3:0] $end
$var reg 4 .! expected_digit1 [3:0] $end
$var reg 4 /! expected_digit0 [3:0] $end
$var parameter 0 0! SCAN_TICK_CYCLES [31:0] $end
$scope module dut $end
$var wire 1 0 clk $end
$var wire 1 1 reset_p $end
$var wire 12 ? current_adc [11:0] $end
$var wire 1 @ display_valid $end
$var wire 4 A an [3:0] $end
$var wire 7 B seg [6:0] $end
$var wire 1 C dp $end
$var reg 12 D frame_adc [11:0] $end
$var reg 1 E frame_valid $end
$var wire 12 ' frame_millivolt [11:0] $end
$var wire 4 3 digit3 [3:0] $end
$var wire 4 4 digit2 [3:0] $end
$var wire 4 5 digit1 [3:0] $end
$var wire 4 6 digit0 [3:0] $end
$var wire 1 : frame_boundary $end
$var parameter 0 F SCAN_TICK_CYCLES [31:0] $end
$scope module u_voltage_display_convert $end
$var wire 12 ! adc_raw [11:0] $end
$var reg 12 " millivolt [11:0] $end
$var reg 24 # scaled_value [23:0] $end
$var reg 13 $ quotient_base [12:0] $end
$var reg 13 % quotient_correction_sum [12:0] $end
$var reg 13 & converted_value [12:0] $end
$upscope $end
$scope module u_voltage_display_bcd $end
$var wire 12 ' millivolt [11:0] $end
$var reg 4 ( digit3 [3:0] $end
$var reg 4 ) digit2 [3:0] $end
$var reg 4 * digit1 [3:0] $end
$var reg 4 + digit0 [3:0] $end
$var reg 28 , shift_register [27:0] $end
$var integer 32 - index [31:0] $end
$upscope $end
$scope module u_voltage_display_scan $end
$var wire 1 0 clk $end
$var wire 1 1 reset_p $end
$var wire 1 2 display_valid $end
$var wire 4 3 digit3 [3:0] $end
$var wire 4 4 digit2 [3:0] $end
$var wire 4 5 digit1 [3:0] $end
$var wire 4 6 digit0 [3:0] $end
$var reg 4 7 an [3:0] $end
$var reg 7 8 seg [6:0] $end
$var reg 1 9 dp $end
$var wire 1 : frame_boundary $end
$var reg 32 ; scan_counter [31:0] $end
$var reg 2 < scan_index [1:0] $end
$var reg 4 = active_digit [3:0] $end
$var parameter 0 > SCAN_TICK_CYCLES [31:0] $end
$scope function digit_to_segments $end
$var reg 7 . digit_to_segments [6:0] $end
$var reg 4 / digit [3:0] $end
$upscope $end
$upscope $end
$upscope $end
$scope module u_conversion_check $end
$var wire 12 G adc_raw [11:0] $end
$var reg 12 H millivolt [11:0] $end
$var reg 24 I scaled_value [23:0] $end
$var reg 13 J quotient_base [12:0] $end
$var reg 13 K quotient_correction_sum [12:0] $end
$var reg 13 L converted_value [12:0] $end
$upscope $end
$scope module u_bcd_check $end
$var wire 12 M millivolt [11:0] $end
$var reg 4 N digit3 [3:0] $end
$var reg 4 O digit2 [3:0] $end
$var reg 4 P digit1 [3:0] $end
$var reg 4 Q digit0 [3:0] $end
$var reg 28 R shift_register [27:0] $end
$var integer 32 S index [31:0] $end
$upscope $end
$scope module u_decoder_check $end
$var wire 1 V clk $end
$var wire 1 W reset_p $end
$var wire 1 X display_valid $end
$var wire 4 Y digit3 [3:0] $end
$var wire 4 Z digit2 [3:0] $end
$var wire 4 [ digit1 [3:0] $end
$var wire 4 \ digit0 [3:0] $end
$var reg 4 ] an [3:0] $end
$var reg 7 ^ seg [6:0] $end
$var reg 1 _ dp $end
$var wire 1 ` frame_boundary $end
$var reg 32 a scan_counter [31:0] $end
$var reg 2 b scan_index [1:0] $end
$var reg 4 c active_digit [3:0] $end
$var parameter 0 d SCAN_TICK_CYCLES [31:0] $end
$scope function digit_to_segments $end
$var reg 7 T digit_to_segments [6:0] $end
$var reg 4 U digit [3:0] $end
$upscope $end
$upscope $end
$scope function expected_segment $end
$var reg 7 e expected_segment [6:0] $end
$var reg 4 f digit [3:0] $end
$upscope $end
$scope task record_error $end
$var reg 960 g message [959:0] $end
$upscope $end
$scope task wait_main_an $end
$var reg 4 h expected_an [3:0] $end
$var integer 32 i guard [31:0] $end
$upscope $end
$scope task wait_decoder_an $end
$var reg 4 j expected_an [3:0] $end
$var integer 32 k guard [31:0] $end
$upscope $end
$scope task check_main_digit $end
$var reg 4 l expected_an [3:0] $end
$var reg 7 m expected_seg [6:0] $end
$var reg 1 n expected_dp $end
$upscope $end
$scope task check_frame $end
$var reg 4 o e3 [3:0] $end
$var reg 4 p e2 [3:0] $end
$var reg 4 q e1 [3:0] $end
$var reg 4 r e0 [3:0] $end
$var reg 1 s valid_value $end
$upscope $end
$scope task apply_and_check $end
$var reg 12 t adc_value [11:0] $end
$var reg 4 u e3 [3:0] $end
$var reg 4 v e2 [3:0] $end
$var reg 4 w e1 [3:0] $end
$var reg 4 x e0 [3:0] $end
$upscope $end
$upscope $end
$enddefinitions $end

#1000000
$dumpvars
b0 !
b110 !!
b0 "
b1000 "!
b11111111111 #
b101 #!
b0 $
1$!
b11111111111 %
b0 %!
b0 &
b1101 &!
b0 '
b1000000 '!
b0 (
1(!
b0 )
b0 )!
b0 *
b1101010010 *!
b0 +
b1010101100 +!
b0 ,
b0 ,!
b1100 -
b110 -!
bx .
b1000 .!
bx /
b100 /!
00
b10 0!
01
02
b0 3
b0 4
b0 5
b0 6
b1101 7
b111111 8
19
0:
b1 ;
b1 <
b0 =
b10 >
b0 ?
0@
b1101 A
b111111 B
1C
b0 D
0E
b10 F
b1101010010 G
b1010101101 H
b1010101101010100000111 I
b1010101101 J
b11110110100 K
b1010101101 L
b1010101101 M
b0 N
b110 O
b1000 P
b101 Q
b11010000101000000000000 R
b1100 S
b1000000 T
b0 U
0V
0W
1X
b0 Y
b0 Z
b0 [
b0 \
b1101 ]
b1000000 ^
1_
0`
b1 a
b1 b
b0 c
b10 d
bx e
bx f
bx g
b111 h
b10 i
bx j
bx k
b111 l
b111111 m
1n
b0 o
b0 p
b0 q
b0 r
0s
bx t
bx u
bx v
bx w
bx x
0y
0z
b0 {
0|
b1101010010 }
b0 ~
$end

#1001000
b110 #!
b1101010011 *!
b1010101101 +!
b101 /!
b1101010011 G
b1010101110 H
b1010101110000111101011 I
b1010101110 J
b10010011001 K
b1010101110 L
b1010101110 M
b110 Q
b11010000110000000000000 R
b1100 S
b1101010011 }

#1002000
b111 #!
b1101010100 *!
b1010101110 +!
b110 /!
b1101010100 G
b1010101111 H
b1010101110111011001111 I
b1000101111101 K
b1010101111 L
b1010101111 M
b111 Q
b11010000111000000000000 R
b1100 S
b1101010100 }

#1003000
b1101010101 *!
b1010101111 +!
b111 /!
b1101010101 G
b1010101111101110110011 I
b1010101111 J
b111001100010 K
b1101010101 }

#1004000
b1000 #!
b1101010110 *!
b1101010110 G
b1010110000 H
b1010110000100010010111 I
b1010110000 J
b101101000111 K
b1010110000 L
b1010110000 M
b1000 Q
b11010001000000000000000 R
b1100 S
b1101010110 }

#1005000
b1001 #!
b1011 &!
b1101010111 *!
b1010110000 +!
b1000 /!
10
b1011 7
b111111 8
b0 ;
b10 <
b1011 A
b1101010111 G
b1010110001 H
b1010110001010101111011 I
b1010110001 J
b100000101100 K
b1010110001 L
b1010110001 M
b1001 Q
b11010001001000000000000 R
b1100 S
1V
b1011 ]
b1000000 ^
b0 a
b10 b
1y
b1101010111 }

#1006000
b1001 "!
b0 #!
b1101011000 *!
b1010110001 +!
b1001 /!
b1101011000 G
b1010110010 H
b1010110010001001011111 I
b1010110010 J
b10100010001 K
b1010110010 L
b1010110010 M
b1001 P
b0 Q
b11010010000000000000000 R
b1100 S
b1101011000 }

#1007000
b1 #!
b1101011001 *!
b1010110010 +!
b1001 .!
b0 /!
b1101011001 G
b1010110011 H
b1010110010111101000011 I
b1000111110101 K
b1010110011 L
b1010110011 M
b1 Q
b11010010001000000000000 R
b1100 S
b1101011001 }

#1008000
b1101011010 *!
b1010110011 +!
b1 /!
b1101011010 G
b1010110011110000100111 I
b1010110011 J
b111011011010 K
b1101011010 }

#1009000
b10 #!
b1101011011 *!
b1101011011 G
b1010110100 H
b1010110100100100001011 I
b1010110100 J
b101110111111 K
b1010110100 L
b1010110100 M
b10 Q
b11010010010000000000000 R
b1100 S
b1101011011 }

#1010000
b11 #!
b1101011100 *!
b1010110100 +!
b10 /!
00
b1101011100 G
b1010110101 H
b1010110101010111101111 I
b1010110101 J
b100010100100 K
b1010110101 L
b1010110101 M
b11 Q
b11010010011000000000000 R
b1100 S
0V
0y
b1101011100 }

#1011000
b100 #!
b1101011101 *!
b1010110101 +!
b11 /!
b1101011101 G
b1010110110 H
b1010110110001011010011 I
b1010110110 J
b10110001001 K
b1010110110 L
b1010110110 M
b100 Q
b11010010100000000000000 R
b1100 S
b1101011101 }

#1012000
b101 #!
b1101011110 *!
b1010110110 +!
b100 /!
b1101011110 G
b1010110111 H
b1010110110111110110111 I
b1001001101101 K
b1010110111 L
b1010110111 M
b101 Q
b11010010101000000000000 R
b1100 S
b1101011110 }

#1013000
b1101011111 *!
b1010110111 +!
b101 /!
b1101011111 G
b1010110111110010011011 I
b1010110111 J
b111101010010 K
b1101011111 }

#1014000
b110 #!
b1101100000 *!
b1101100000 G
b1010111000 H
b1010111000100101111111 I
b1010111000 J
b110000110111 K
b1010111000 L
b1010111000 M
b110 Q
b11010010110000000000000 R
b1100 S
b1101100000 }

#1015000
b111 #!
b1101100001 *!
b1010111000 +!
b110 /!
10
b1 ;
b1101100001 G
b1010111001 H
b1010111001011001100011 I
b1010111001 J
b100100011100 K
b1010111001 L
b1010111001 M
b111 Q
b11010010111000000000000 R
b1100 S
1V
b1 a
1y
b1101100001 }

#1016000
b1000 #!
b1101100010 *!
b1010111001 +!
b111 /!
b1101100010 G
b1010111010 H
b1010111010001101000111 I
b1010111010 J
b11000000001 K
b1010111010 L
b1010111010 M
b1000 Q
b11010011000000000000000 R
b1100 S
b1101100010 }

#1017000
b1001 #!
b1101100011 *!
b1010111010 +!
b1000 /!
b1101100011 G
b1010111011 H
b1010111011000000101011 I
b1010111011 J
b1011100110 K
b1010111011 L
b1010111011 M
b1001 Q
b11010011001000000000000 R
b1100 S
b1101100011 }

#1018000
b1101100100 *!
b1010111011 +!
b1001 /!
b1101100100 G
b1010111011110100001111 I
b111111001010 K
b1101100100 }

#1019000
b111 !!
b0 "!
b0 #!
b1101100101 *!
b1101100101 G
b1010111100 H
b1010111100100111110011 I
b1010111100 J
b110010101111 K
b1010111100 L
b1010111100 M
b111 O
b0 P
b0 Q
b11100000000000000000000 R
b1100 S
b1101100101 }

#1020000
b1 #!
b1101100110 *!
b1010111100 +!
b111 -!
b0 .!
b0 /!
00
b1101100110 G
b1010111101 H
b1010111101011011010111 I
b1010111101 J
b100110010100 K
b1010111101 L
b1010111101 M
b1 Q
b11100000001000000000000 R
b1100 S
0V
0y
b1101100110 }

#1021000
b10 #!
b1101100111 *!
b1010111101 +!
b1 /!
b1101100111 G
b1010111110 H
b1010111110001110111011 I
b1010111110 J
b11001111001 K
b1010111110 L
b1010111110 M
b10 Q
b11100000010000000000000 R
b1100 S
b1101100111 }

#1022000
b11 #!
b1101101000 *!
b1010111110 +!
b10 /!
b1101101000 G
b1010111111 H
b1010111111000010011111 I
b1010111111 J
b1101011110 K
b1010111111 L
b1010111111 M
b11 Q
b11100000011000000000000 R
b1100 S
b1101101000 }

#1023000
b100 #!
b1101101001 *!
b1010111111 +!
b11 /!
b1101101001 G
b1011000000 H
b1010111111110110000011 I
b1000001000010 K
b1011000000 L
b1011000000 M
b100 Q
b11100000100000000000000 R
b1100 S
b1101101001 }

#1024000
b1101101010 *!
b1011000000 +!
b100 /!
b1101101010 G
b1011000000101001100111 I
b1011000000 J
b110100100111 K
b1101101010 }

#1025000
b101 #!
b111 &!
0(!
b1101101011 *!
10
b111 7
b111111 8
b0 ;
b11 <
b111 A
b1101101011 G
b1011000001 H
b1011000001011101001011 I
b1011000001 J
b101000001100 K
b1011000001 L
b1011000001 M
b101 Q
b11100000101000000000000 R
b1100 S
1V
b111 ]
b1000000 ^
0_
b0 a
b11 b
1y
b1101101011 }

